sbmlsim/__init__.py
sbmlsim/data.py
sbmlsim/serialization.py
sbmlsim/units.py
sbmlsim/utils.py
sbmlsim/combine/TODO_SEDML.md
sbmlsim/combine/__init__.py
sbmlsim/combine/datagenerator.py
sbmlsim/combine/mathml.py
sbmlsim/combine/validation.py
sbmlsim/combine/examples/__init__.py
sbmlsim/combine/examples/execute_omex.py
sbmlsim/combine/examples/execute_sedml.py
sbmlsim/combine/examples/l1v4/BIOMD0000000012_urn.xml
sbmlsim/combine/examples/l1v4/algorithm_parameters.sedml
sbmlsim/combine/examples/l1v4/axis.sedml
sbmlsim/combine/examples/l1v4/axis_grids.png
sbmlsim/combine/examples/l1v4/axis_grids.sedml
sbmlsim/combine/examples/l1v4/axis_minmax.png
sbmlsim/combine/examples/l1v4/axis_minmax.sedml
sbmlsim/combine/examples/l1v4/axis_minmax_smaller.png
sbmlsim/combine/examples/l1v4/axis_minmax_smaller.sedml
sbmlsim/combine/examples/l1v4/axis_minormax.png
sbmlsim/combine/examples/l1v4/axis_minormax.sedml
sbmlsim/combine/examples/l1v4/case_01.xml
sbmlsim/combine/examples/l1v4/case_02.xml
sbmlsim/combine/examples/l1v4/case_03.xml
sbmlsim/combine/examples/l1v4/concentration_amount.plot_0.png
sbmlsim/combine/examples/l1v4/concentration_amount.plot_1.png
sbmlsim/combine/examples/l1v4/concentration_amount.plot_2.png
sbmlsim/combine/examples/l1v4/concentration_amount.sedml
sbmlsim/combine/examples/l1v4/concentration_amount_b.plot_0.png
sbmlsim/combine/examples/l1v4/concentration_amount_b.plot_1.png
sbmlsim/combine/examples/l1v4/concentration_amount_b.plot_2.png
sbmlsim/combine/examples/l1v4/concentration_amount_b.sedml
sbmlsim/combine/examples/l1v4/curve_types.sedml
sbmlsim/combine/examples/l1v4/curve_types_errors.sedml
sbmlsim/combine/examples/l1v4/curve_types_model.xml
sbmlsim/combine/examples/l1v4/heat_map_ls.sedml
sbmlsim/combine/examples/l1v4/hill.xml
sbmlsim/combine/examples/l1v4/jacobian.sedml
sbmlsim/combine/examples/l1v4/line_overlap_order.sedml
sbmlsim/combine/examples/l1v4/linetype.sedml
sbmlsim/combine/examples/l1v4/logxy.sedml
sbmlsim-0.3.0.dist-info/METADATA
sbmlsim-0.3.0.dist-info/WHEEL
sbmlsim-0.3.0.dist-info/licenses/LICENSE
sbmlsim-0.3.0.dist-info/RECORD
