Metadata-Version: 2.4
Name: sbmlsim
Version: 0.3.0
Summary: sbmlsim are utilities for the simulation of SBML models.
Author-email: Matthias König <konigmatt@googlemail.com>
Maintainer-email: Matthias König <konigmatt@googlemail.com>
License-File: LICENSE
Keywords: COMBINE,SBML,modeling,standardization
Classifier: Development Status :: 4 - Beta
Classifier: Intended Audience :: Science/Research
Classifier: License :: OSI Approved :: MIT License
Classifier: Operating System :: OS Independent
Classifier: Programming Language :: Python :: 3.13
Classifier: Programming Language :: Python :: 3.14
Classifier: Programming Language :: Python :: Implementation :: CPython
Classifier: Topic :: Scientific/Engineering
Classifier: Topic :: Scientific/Engineering :: Bio-Informatics
Requires-Python: >=3.13
Requires-Dist: altair>=5.5.0
Requires-Dist: bottleneck>=1.4.2
Requires-Dist: dill>=0.4.0
Requires-Dist: jinja2
Requires-Dist: libroadrunner
Requires-Dist: matplotlib
Requires-Dist: numpy
Requires-Dist: pandas
Requires-Dist: petab>=0.8.1
Requires-Dist: pint
Requires-Dist: pkdb-analysis>=0.3.1
Requires-Dist: plotly>=6.0.0
Requires-Dist: psutil>=6.1.1
Requires-Dist: pydantic
Requires-Dist: pydoe>=0.3.8
Requires-Dist: pymetadata>=0.5.10
Requires-Dist: python-libnuml>=1.1.7
Requires-Dist: python-libsbml
Requires-Dist: python-libsedml>=2.0.33
Requires-Dist: rich
Requires-Dist: salib>=1.5.2
Requires-Dist: sbmlutils>=0.9.6
Requires-Dist: scipy
Requires-Dist: seaborn>=0.13.2
Requires-Dist: setproctitle>=1.3.4
Requires-Dist: statsmodels>=0.14.6
Requires-Dist: sympy
Requires-Dist: typst>=0.14.5
Requires-Dist: xarray>=2025.11.0
Requires-Dist: xmltodict>=0.14.2
Provides-Extra: dev
Requires-Dist: bump-my-version>=1.2.4; extra == 'dev'
Requires-Dist: mypy>=1.18.2; extra == 'dev'
Requires-Dist: pre-commit>=4.0.1; extra == 'dev'
Requires-Dist: pytest-cov>=7.0.0; extra == 'dev'
Requires-Dist: pytest>=8.4.2; extra == 'dev'
Requires-Dist: ruff>=0.14.0; extra == 'dev'
Requires-Dist: tox>=4.31.0; extra == 'dev'
